LICENSE
README.md
trackingmore/__init__.py
trackingmore/air_waybill.py
trackingmore/const.py
trackingmore/courier.py
trackingmore/exception.py
trackingmore/request.py
trackingmore/response.py
trackingmore/tracking.py
trackingmore/util.py
trackingmore_sdk_python-0.1.3.dist-info/LICENSE
trackingmore_sdk_python-0.1.3.dist-info/METADATA
trackingmore_sdk_python-0.1.3.dist-info/WHEEL
trackingmore_sdk_python-0.1.3.dist-info/RECORD
