Metadata-Version: 2.1
Name: trackingmore-sdk-python
Version: 0.1.3
Summary: The Python SDK of Trackingmore API
Home-page: https://www.trackingmore.com/docs/trackingmore/d5ac362fc3cda-api-quick-start
Keywords: trackingmore,api,tracking
Author: TrackingMore
Author-email: manage@trackingmore.org
Requires-Python: >=3.7,<4.0
Classifier: Programming Language :: Python :: 3
Classifier: Programming Language :: Python :: 3.7
Classifier: Programming Language :: Python :: 3.8
Classifier: Programming Language :: Python :: 3.9
Classifier: Programming Language :: Python :: 3.10
Classifier: Programming Language :: Python :: 3.11
Requires-Dist: requests (>=2.31.0,<3.0.0)
Requires-Dist: urllib3 (==1.26.7)
Project-URL: Documentation, https://github.com/TrackingMores/trackingmore-sdk-python
Project-URL: Repository, https://github.com/TrackingMores/trackingmore-sdk-python
